[{"id":6,"uuid":"wewqsd6","title":"Hamburger and French Fry","price":"546","src":"646eac316a9f8_Hamburger-And-French-Fries.jpg","alt":"Hamburger and French Fry","e_sale":"on","outdore":"on","cost_price":"416","type":"fast Food","date":"2023-05-25 00:30:41","status":true},{"id":7,"uuid":"wewqsd7","title":"Chicken Rool","price":"300","src":"646eacacb4646_wendys-Grilled-Chicken-Ranch-Wrap-032423-3ffe1174a94d429aac4b6c67cfe77455.jpg","alt":"chicken rool","e_sale":"on","outdore":"on","cost_price":"287","type":"Fast Food","date":"2023-05-25 00:32:44","status":true}]